widgetastic.bootstrap-0.1.2.dist-info/METADATA
widgetastic.bootstrap-0.1.2.dist-info/RECORD
widgetastic.bootstrap-0.1.2.dist-info/WHEEL
widgetastic.bootstrap-0.1.2.dist-info/top_level.txt
widgetastic_bootstrap/__init__.py
widgetastic_bootstrap/accordion.py
widgetastic_bootstrap/breadcrumb.py
widgetastic_bootstrap/button.py
widgetastic_bootstrap/carousel.py
widgetastic_bootstrap/dropdown.py
widgetastic_bootstrap/tab.py
