Metadata-Version: 2.1
Name: widgetastic.bootstrap
Version: 0.1.2
Summary: Twitter Bootstrap widget library for Widgetastic
Home-page: https://github.com/quarckster/widgetastic.bootstrap
Author: Dmitry Misharov
Author-email: misharov@redhat.com
License: Apache license
Platform: UNKNOWN
Classifier: Programming Language :: Python
Classifier: Programming Language :: Python :: 2.7
Classifier: Programming Language :: Python :: 3.6
Classifier: Topic :: Software Development :: Libraries :: Python Modules
Classifier: Topic :: Software Development :: Quality Assurance
Classifier: Topic :: Software Development :: Testing
Requires-Dist: widgetastic.core (>=0.10.0)
